[
  {
    "network": [
      {
        "file": "PLO_6_10_0.05-0.10.json",
        "value": "10",
        "data": {
          "rank": "9",
          "network": "888Poker",
          "currency": "$0.89",
          "bigBlinds": "8.92 BB",
          "netRake": "4.46%",
          "rakePercentage": "5.00%",
          "rakeCap": "$4.00 cap",
          "rule": "No flop no drop (rake is taken only when the hand goes to a flop)",
          "operators": "888Poker"
        }
      },
      {
        "file": "PLO_6_25_0.10-0.25.json",
        "value": "25",
        "data": {
          "rank": "10",
          "network": "888Poker",
          "currency": "$2.23",
          "bigBlinds": "8.90 BB",
          "netRake": "4.45%",
          "rakePercentage": "5.00%",
          "rakeCap": "$4.00 cap",
          "rule": "No flop no drop (rake is taken only when the hand goes to a flop)",
          "operators": "888Poker"
        }
      },
      {
        "file": "PLO_6_50_0.25-0.50.json",
        "value": "50",
        "data": {
          "rank": "7",
          "network": "888Poker",
          "currency": "$4.21",
          "bigBlinds": "8.43 BB",
          "netRake": "4.15%",
          "rakePercentage": "5.00%",
          "rakeCap": "$4.00 cap",
          "rule": "No flop no drop (rake is taken only when the hand goes to a flop)",
          "operators": "888Poker"
        }
      },
      {
        "file": "PLO_6_100_0.50-1.00.json",
        "value": "100",
        "data": {
          "rank": "6",
          "network": "888Poker",
          "currency": "$7.66",
          "bigBlinds": "7.66 BB",
          "netRake": "3.69%",
          "rakePercentage": "5.00%",
          "rakeCap": "$4.00 cap",
          "rule": "No flop no drop (rake is taken only when the hand goes to a flop)",
          "operators": "888Poker"
        }
      },
      {
        "file": "PLO_6_200_1.00-2.00.json",
        "value": "200",
        "data": {
          "rank": "6",
          "network": "888Poker",
          "currency": "$10.71",
          "bigBlinds": "5.35 BB",
          "netRake": "2.81%",
          "rakePercentage": "5.00%",
          "rakeCap": "$4.00 cap",
          "rule": "No flop no drop (rake is taken only when the hand goes to a flop)",
          "operators": "888Poker"
        }
      },
      {
        "file": "PLO_6_500_2.50-5.00.json",
        "value": "500",
        "data": {
          "rank": "6",
          "network": "888Poker",
          "currency": "$18.27",
          "bigBlinds": "3.65 BB",
          "netRake": "1.92%",
          "rakePercentage": "5.00%",
          "rakeCap": "$4.00 cap",
          "rule": "No flop no drop (rake is taken only when the hand goes to a flop)",
          "operators": "888Poker"
        }
      }
    ],
    "name": "888Poker"
  },
  {
    "network": [
      {
        "file": "PLO_6_10_0.05-0.10.json",
        "value": "10",
        "data": {
          "rank": "12",
          "network": "Chico Poker",
          "currency": "$1.11",
          "bigBlinds": "11.07 BB",
          "netRake": "5.54%",
          "rakePercentage": "6.25%",
          "rakeCap": "$1.50 cap",
          "rule": "No flop no drop (rake is taken only when the hand goes to a flop)",
          "operators": "TigerGamingBetOnline.agSportsBetting.ag"
        }
      },
      {
        "file": "PLO_6_25_0.10-0.25.json",
        "value": "25",
        "data": {
          "rank": "13",
          "network": "Chico Poker",
          "currency": "$2.65",
          "bigBlinds": "10.60 BB",
          "netRake": "5.31%",
          "rakePercentage": "6.25%",
          "rakeCap": "$2.50 cap",
          "rule": "No flop no drop (rake is taken only when the hand goes to a flop)",
          "operators": "TigerGamingBetOnline.agSportsBetting.ag"
        }
      },
      {
        "file": "PLO_6_50_0.25-0.50.json",
        "value": "50",
        "data": {
          "rank": "13",
          "network": "Chico Poker",
          "currency": "$4.51",
          "bigBlinds": "9.01 BB",
          "netRake": "4.44%",
          "rakePercentage": "5.56%",
          "rakeCap": "$3.50 cap",
          "rule": "No flop no drop (rake is taken only when the hand goes to a flop)",
          "operators": "TigerGamingBetOnline.agSportsBetting.ag"
        }
      },
      {
        "file": "PLO_6_100_0.50-1.00.json",
        "value": "100",
        "data": {
          "rank": "13",
          "network": "Chico Poker",
          "currency": "$8.29",
          "bigBlinds": "8.29 BB",
          "netRake": "3.99%",
          "rakePercentage": "5.56%",
          "rakeCap": "$4.00 cap",
          "rule": "No flop no drop (rake is taken only when the hand goes to a flop)",
          "operators": "TigerGamingBetOnline.agSportsBetting.ag"
        }
      },
      {
        "file": "PLO_6_200_1.00-2.00.json",
        "value": "200",
        "data": {
          "rank": "11",
          "network": "Chico Poker",
          "currency": "$11.46",
          "bigBlinds": "5.73 BB",
          "netRake": "3.01%",
          "rakePercentage": "5.56%",
          "rakeCap": "$4.00 cap",
          "rule": "No flop no drop (rake is taken only when the hand goes to a flop)",
          "operators": "TigerGamingBetOnline.agSportsBetting.ag"
        }
      },
      {
        "file": "PLO_6_500_2.50-5.00.json",
        "value": "500",
        "data": {
          "rank": "11",
          "network": "Chico Poker",
          "currency": "$24.92",
          "bigBlinds": "4.98 BB",
          "netRake": "2.61%",
          "rakePercentage": "5.56%",
          "rakeCap": "$7.00 cap",
          "rule": "No flop no drop (rake is taken only when the hand goes to a flop)",
          "operators": "TigerGamingBetOnline.agSportsBetting.ag"
        }
      }
    ],
    "name": "Chico Poker"
  },
  {
    "network": [
      {
        "file": "PLO_6_10_0.05-0.10.json",
        "value": "10",
        "data": {
          "rank": "5",
          "network": "CoinPoker",
          "currency": "$0.84",
          "bigBlinds": "8.40 BB",
          "netRake": "4.20%",
          "rakePercentage": "5.00%",
          "rakeCap": "$0.75 cap",
          "rule": "No flop no drop (rake is taken only when the hand goes to a flop)",
          "operators": "CoinPoker"
        }
      },
      {
        "file": "PLO_6_25_0.10-0.25.json",
        "value": "25",
        "data": {
          "rank": "4",
          "network": "CoinPoker",
          "currency": "$2.08",
          "bigBlinds": "8.30 BB",
          "netRake": "4.16%",
          "rakePercentage": "5.00%",
          "rakeCap": "$1.75 cap",
          "rule": "No flop no drop (rake is taken only when the hand goes to a flop)",
          "operators": "CoinPoker"
        }
      },
      {
        "file": "PLO_6_50_0.25-0.50.json",
        "value": "50",
        "data": {
          "rank": "4",
          "network": "CoinPoker",
          "currency": "$3.80",
          "bigBlinds": "7.60 BB",
          "netRake": "3.75%",
          "rakePercentage": "5.00%",
          "rakeCap": "$2.25 cap",
          "rule": "No flop no drop (rake is taken only when the hand goes to a flop)",
          "operators": "CoinPoker"
        }
      },
      {
        "file": "PLO_6_100_0.50-1.00.json",
        "value": "100",
        "data": {
          "rank": "1",
          "network": "CoinPoker",
          "currency": "$6.73",
          "bigBlinds": "6.73 BB",
          "netRake": "3.24%",
          "rakePercentage": "5.00%",
          "rakeCap": "$2.50 cap",
          "rule": "No flop no drop (rake is taken only when the hand goes to a flop)",
          "operators": "CoinPoker"
        }
      },
      {
        "file": "PLO_6_200_1.00-2.00.json",
        "value": "200",
        "data": {
          "rank": "2",
          "network": "CoinPoker",
          "currency": "$9.63",
          "bigBlinds": "4.81 BB",
          "netRake": "2.52%",
          "rakePercentage": "5.00%",
          "rakeCap": "$3.00 cap",
          "rule": "No flop no drop (rake is taken only when the hand goes to a flop)",
          "operators": "CoinPoker"
        }
      },
      {
        "file": "PLO_6_500_2.50-5.00.json",
        "value": "500",
        "data": {
          "rank": "10",
          "network": "CoinPoker",
          "currency": "$20.28",
          "bigBlinds": "4.06 BB",
          "netRake": "2.13%",
          "rakePercentage": "5.00%",
          "rakeCap": "$5.00 cap",
          "rule": "No flop no drop (rake is taken only when the hand goes to a flop)",
          "operators": "CoinPoker"
        }
      }
    ],
    "name": "CoinPoker"
  },
  {
    "network": [
      {
        "file": "PLO_6_10_0.05-0.10.json",
        "value": "10",
        "data": {
          "rank": "2",
          "network": "GGPoker",
          "currency": "$0.72",
          "bigBlinds": "7.21 BB",
          "netRake": "3.61%",
          "rakePercentage": "5.00%",
          "rakeCap": "$0.30 cap",
          "rule": "Three-bet or flop (rake is taken a three-bet happens or when the hand goes to a flop)",
          "operators": "GGPoker"
        }
      },
      {
        "file": "PLO_6_25_0.10-0.25.json",
        "value": "25",
        "data": {
          "rank": "1",
          "network": "GGPoker",
          "currency": "$1.80",
          "bigBlinds": "7.21 BB",
          "netRake": "3.61%",
          "rakePercentage": "5.00%",
          "rakeCap": "$0.75 cap",
          "rule": "Three-bet or flop (rake is taken a three-bet happens or when the hand goes to a flop)",
          "operators": "GGPoker"
        }
      },
      {
        "file": "PLO_6_50_0.25-0.50.json",
        "value": "50",
        "data": {
          "rank": "1",
          "network": "GGPoker",
          "currency": "$3.30",
          "bigBlinds": "6.60 BB",
          "netRake": "3.25%",
          "rakePercentage": "5.00%",
          "rakeCap": "$1.00 cap",
          "rule": "Three-bet or flop (rake is taken a three-bet happens or when the hand goes to a flop)",
          "operators": "GGPoker"
        }
      },
      {
        "file": "PLO_6_100_0.50-1.00.json",
        "value": "100",
        "data": {
          "rank": "3",
          "network": "GGPoker",
          "currency": "$6.77",
          "bigBlinds": "6.77 BB",
          "netRake": "3.26%",
          "rakePercentage": "5.00%",
          "rakeCap": "$2.00 cap",
          "rule": "Three-bet or flop (rake is taken a three-bet happens or when the hand goes to a flop)",
          "operators": "GGPoker"
        }
      },
      {
        "file": "PLO_6_200_1.00-2.00.json",
        "value": "200",
        "data": {
          "rank": "12",
          "network": "GGPoker",
          "currency": "$12.01",
          "bigBlinds": "6.00 BB",
          "netRake": "3.15%",
          "rakePercentage": "5.00%",
          "rakeCap": "$4.00 cap",
          "rule": "Three-bet or flop (rake is taken a three-bet happens or when the hand goes to a flop)",
          "operators": "GGPoker"
        }
      },
      {
        "file": "PLO_6_500_2.50-5.00.json",
        "value": "500",
        "data": {
          "rank": "13",
          "network": "GGPoker",
          "currency": "$27.25",
          "bigBlinds": "5.45 BB",
          "netRake": "2.86%",
          "rakePercentage": "5.00%",
          "rakeCap": "$7.50 cap",
          "rule": "Three-bet or flop (rake is taken a three-bet happens or when the hand goes to a flop)",
          "operators": "GGPoker"
        }
      }
    ],
    "name": "GGPoker"
  },
  {
    "network": [
      {
        "file": "PLO_6_10_0.05-0.10.json",
        "value": "10",
        "data": {
          "rank": "6",
          "network": "Horizon Poker",
          "currency": "$0.89",
          "bigBlinds": "8.91 BB",
          "netRake": "4.46%",
          "rakePercentage": "5.00%",
          "rakeCap": "$2.00 cap",
          "rule": "No flop no drop (rake is taken only when the hand goes to a flop)",
          "operators": "Juicy StakesEverygame"
        }
      },
      {
        "file": "PLO_6_25_0.10-0.25.json",
        "value": "25",
        "data": {
          "rank": "7",
          "network": "Horizon Poker",
          "currency": "$2.21",
          "bigBlinds": "8.85 BB",
          "netRake": "4.43%",
          "rakePercentage": "5.00%",
          "rakeCap": "$3.00 cap",
          "rule": "No flop no drop (rake is taken only when the hand goes to a flop)",
          "operators": "Juicy StakesEverygame"
        }
      },
      {
        "file": "PLO_6_50_0.25-0.50.json",
        "value": "50",
        "data": {
          "rank": "7",
          "network": "Horizon Poker",
          "currency": "$4.21",
          "bigBlinds": "8.43 BB",
          "netRake": "4.15%",
          "rakePercentage": "5.00%",
          "rakeCap": "$4.00 cap",
          "rule": "No flop no drop (rake is taken only when the hand goes to a flop)",
          "operators": "Juicy StakesEverygame"
        }
      },
      {
        "file": "PLO_6_100_0.50-1.00.json",
        "value": "100",
        "data": {
          "rank": "6",
          "network": "Horizon Poker",
          "currency": "$7.66",
          "bigBlinds": "7.66 BB",
          "netRake": "3.69%",
          "rakePercentage": "5.00%",
          "rakeCap": "$4.00 cap",
          "rule": "No flop no drop (rake is taken only when the hand goes to a flop)",
          "operators": "Juicy StakesEverygame"
        }
      },
      {
        "file": "PLO_6_200_1.00-2.00.json",
        "value": "200",
        "data": {
          "rank": "6",
          "network": "Horizon Poker",
          "currency": "$10.71",
          "bigBlinds": "5.35 BB",
          "netRake": "2.81%",
          "rakePercentage": "5.00%",
          "rakeCap": "$4.00 cap",
          "rule": "No flop no drop (rake is taken only when the hand goes to a flop)",
          "operators": "Juicy StakesEverygame"
        }
      },
      {
        "file": "PLO_6_500_2.50-5.00.json",
        "value": "500",
        "data": {
          "rank": "6",
          "network": "Horizon Poker",
          "currency": "$18.27",
          "bigBlinds": "3.65 BB",
          "netRake": "1.92%",
          "rakePercentage": "5.00%",
          "rakeCap": "$4.00 cap",
          "rule": "No flop no drop (rake is taken only when the hand goes to a flop)",
          "operators": "Juicy StakesEverygame"
        }
      }
    ],
    "name": "Horizon Poker"
  },
  {
    "network": [
      {
        "file": "PLO_6_10_0.05-0.10.json",
        "value": "10",
        "data": {
          "rank": "13",
          "network": "iPoker Network",
          "currency": "€1.19",
          "bigBlinds": "11.87 BB",
          "netRake": "5.94%",
          "rakePercentage": "6.67%",
          "rakeCap": "€2.00 cap",
          "rule": "No flop no drop (rake is taken only when the hand goes to a flop)",
          "operators": "BetssonWilliam Hillbet-at-home"
        }
      },
      {
        "file": "PLO_6_25_0.10-0.25.json",
        "value": "25",
        "data": {
          "rank": "5",
          "network": "iPoker Network",
          "currency": "€2.12",
          "bigBlinds": "8.48 BB",
          "netRake": "4.25%",
          "rakePercentage": "5.00%",
          "rakeCap": "€2.00 cap",
          "rule": "No flop no drop (rake is taken only when the hand goes to a flop)",
          "operators": "BetssonWilliam Hillbet-at-home"
        }
      },
      {
        "file": "PLO_6_50_0.25-0.50.json",
        "value": "50",
        "data": {
          "rank": "5",
          "network": "iPoker Network",
          "currency": "€4.02",
          "bigBlinds": "8.04 BB",
          "netRake": "3.96%",
          "rakePercentage": "5.00%",
          "rakeCap": "€3.00 cap",
          "rule": "No flop no drop (rake is taken only when the hand goes to a flop)",
          "operators": "BetssonWilliam Hillbet-at-home"
        }
      },
      {
        "file": "PLO_6_100_0.50-1.00.json",
        "value": "100",
        "data": {
          "rank": "6",
          "network": "iPoker Network",
          "currency": "€7.66",
          "bigBlinds": "7.66 BB",
          "netRake": "3.69%",
          "rakePercentage": "5.00%",
          "rakeCap": "€4.00 cap",
          "rule": "No flop no drop (rake is taken only when the hand goes to a flop)",
          "operators": "BetssonWilliam Hillbet-at-home"
        }
      },
      {
        "file": "PLO_6_200_1.00-2.00.json",
        "value": "200",
        "data": {
          "rank": "6",
          "network": "iPoker Network",
          "currency": "€10.71",
          "bigBlinds": "5.35 BB",
          "netRake": "2.81%",
          "rakePercentage": "5.00%",
          "rakeCap": "€4.00 cap",
          "rule": "No flop no drop (rake is taken only when the hand goes to a flop)",
          "operators": "BetssonWilliam Hillbet-at-home"
        }
      },
      {
        "file": "PLO_6_500_2.50-5.00.json",
        "value": "500",
        "data": {
          "rank": "6",
          "network": "iPoker Network",
          "currency": "€18.27",
          "bigBlinds": "3.65 BB",
          "netRake": "1.92%",
          "rakePercentage": "5.00%",
          "rakeCap": "€4.00 cap",
          "rule": "No flop no drop (rake is taken only when the hand goes to a flop)",
          "operators": "BetssonWilliam Hillbet-at-home"
        }
      }
    ],
    "name": "iPoker Network"
  },
  {
    "network": [
      {
        "file": "PLO_6_10_0.05-0.10.json",
        "value": "10",
        "data": {
          "rank": "4",
          "network": "JackPoker",
          "currency": "$0.80",
          "bigBlinds": "7.96 BB",
          "netRake": "3.99%",
          "rakePercentage": "5.50%",
          "rakeCap": "$0.40 cap",
          "rule": "No flop no drop (rake is taken only when the hand goes to a flop)",
          "operators": "JackPoker"
        }
      },
      {
        "file": "PLO_6_25_0.10-0.25.json",
        "value": "25",
        "data": {
          "rank": "3",
          "network": "JackPoker",
          "currency": "$1.87",
          "bigBlinds": "7.48 BB",
          "netRake": "3.75%",
          "rakePercentage": "5.50%",
          "rakeCap": "$0.80 cap",
          "rule": "No flop no drop (rake is taken only when the hand goes to a flop)",
          "operators": "JackPoker"
        }
      },
      {
        "file": "PLO_6_50_0.25-0.50.json",
        "value": "50",
        "data": {
          "rank": "2",
          "network": "JackPoker",
          "currency": "$3.59",
          "bigBlinds": "7.18 BB",
          "netRake": "3.54%",
          "rakePercentage": "5.50%",
          "rakeCap": "$1.40 cap",
          "rule": "No flop no drop (rake is taken only when the hand goes to a flop)",
          "operators": "JackPoker"
        }
      },
      {
        "file": "PLO_6_100_0.50-1.00.json",
        "value": "100",
        "data": {
          "rank": "5",
          "network": "JackPoker",
          "currency": "$7.18",
          "bigBlinds": "7.18 BB",
          "netRake": "3.46%",
          "rakePercentage": "5.50%",
          "rakeCap": "$2.50 cap",
          "rule": "No flop no drop (rake is taken only when the hand goes to a flop)",
          "operators": "JackPoker"
        }
      },
      {
        "file": "PLO_6_200_1.00-2.00.json",
        "value": "200",
        "data": {
          "rank": "13",
          "network": "JackPoker",
          "currency": "$12.30",
          "bigBlinds": "6.15 BB",
          "netRake": "3.22%",
          "rakePercentage": "5.50%",
          "rakeCap": "$5.00 cap",
          "rule": "No flop no drop (rake is taken only when the hand goes to a flop)",
          "operators": "JackPoker"
        }
      },
      {
        "file": "PLO_6_500_2.50-5.00.json",
        "value": "500",
        "data": {
          "rank": "12",
          "network": "JackPoker",
          "currency": "$25.48",
          "bigBlinds": "5.10 BB",
          "netRake": "2.67%",
          "rakePercentage": "5.50%",
          "rakeCap": "$7.50 cap",
          "rule": "No flop no drop (rake is taken only when the hand goes to a flop)",
          "operators": "JackPoker"
        }
      }
    ],
    "name": "JackPoker"
  },
  {
    "network": [
      {
        "file": "PLO_6_10_0.05-0.10.json",
        "value": "10",
        "data": {
          "rank": "6",
          "network": "PaiWangLuo",
          "currency": "$0.89",
          "bigBlinds": "8.91 BB",
          "netRake": "4.46%",
          "rakePercentage": "5.00%",
          "rakeCap": "$2.00 cap",
          "rule": "No flop no drop (rake is taken only when the hand goes to a flop)",
          "operators": "IgnitionBovadaBodog"
        }
      },
      {
        "file": "PLO_6_25_0.10-0.25.json",
        "value": "25",
        "data": {
          "rank": "5",
          "network": "PaiWangLuo",
          "currency": "$2.12",
          "bigBlinds": "8.48 BB",
          "netRake": "4.25%",
          "rakePercentage": "5.00%",
          "rakeCap": "$2.00 cap",
          "rule": "No flop no drop (rake is taken only when the hand goes to a flop)",
          "operators": "IgnitionBovadaBodog"
        }
      },
      {
        "file": "PLO_6_50_0.25-0.50.json",
        "value": "50",
        "data": {
          "rank": "7",
          "network": "PaiWangLuo",
          "currency": "$4.21",
          "bigBlinds": "8.43 BB",
          "netRake": "4.15%",
          "rakePercentage": "5.00%",
          "rakeCap": "$4.00 cap",
          "rule": "No flop no drop (rake is taken only when the hand goes to a flop)",
          "operators": "IgnitionBovadaBodog"
        }
      },
      {
        "file": "PLO_6_100_0.50-1.00.json",
        "value": "100",
        "data": {
          "rank": "6",
          "network": "PaiWangLuo",
          "currency": "$7.66",
          "bigBlinds": "7.66 BB",
          "netRake": "3.69%",
          "rakePercentage": "5.00%",
          "rakeCap": "$4.00 cap",
          "rule": "No flop no drop (rake is taken only when the hand goes to a flop)",
          "operators": "IgnitionBovadaBodog"
        }
      },
      {
        "file": "PLO_6_200_1.00-2.00.json",
        "value": "200",
        "data": {
          "rank": "6",
          "network": "PaiWangLuo",
          "currency": "$10.71",
          "bigBlinds": "5.35 BB",
          "netRake": "2.81%",
          "rakePercentage": "5.00%",
          "rakeCap": "$4.00 cap",
          "rule": "No flop no drop (rake is taken only when the hand goes to a flop)",
          "operators": "IgnitionBovadaBodog"
        }
      },
      {
        "file": "PLO_6_500_2.50-5.00.json",
        "value": "500",
        "data": {
          "rank": "6",
          "network": "PaiWangLuo",
          "currency": "$18.27",
          "bigBlinds": "3.65 BB",
          "netRake": "1.92%",
          "rakePercentage": "5.00%",
          "rakeCap": "$4.00 cap",
          "rule": "No flop no drop (rake is taken only when the hand goes to a flop)",
          "operators": "IgnitionBovadaBodog"
        }
      }
    ],
    "name": "PaiWangLuo"
  },
  {
    "network": [
      {
        "file": "PLO_6_10_0.05-0.10.json",
        "value": "10",
        "data": {
          "rank": "3",
          "network": "PokerStars",
          "currency": "$0.76",
          "bigBlinds": "7.57 BB",
          "netRake": "3.79%",
          "rakePercentage": "4.25%",
          "rakeCap": "$1.50 cap",
          "rule": "No flop no drop (rake is taken only when the hand goes to a flop)",
          "operators": "PokerStars"
        }
      },
      {
        "file": "PLO_6_25_0.10-0.25.json",
        "value": "25",
        "data": {
          "rank": "2",
          "network": "PokerStars",
          "currency": "$1.85",
          "bigBlinds": "7.38 BB",
          "netRake": "3.69%",
          "rakePercentage": "4.25%",
          "rakeCap": "$2.00 cap",
          "rule": "No flop no drop (rake is taken only when the hand goes to a flop)",
          "operators": "PokerStars"
        }
      },
      {
        "file": "PLO_6_50_0.25-0.50.json",
        "value": "50",
        "data": {
          "rank": "3",
          "network": "PokerStars",
          "currency": "$3.70",
          "bigBlinds": "7.40 BB",
          "netRake": "3.65%",
          "rakePercentage": "5.00%",
          "rakeCap": "$2.00 cap",
          "rule": "No flop no drop (rake is taken only when the hand goes to a flop)",
          "operators": "PokerStars"
        }
      },
      {
        "file": "PLO_6_100_0.50-1.00.json",
        "value": "100",
        "data": {
          "rank": "1",
          "network": "PokerStars",
          "currency": "$6.73",
          "bigBlinds": "6.73 BB",
          "netRake": "3.24%",
          "rakePercentage": "5.00%",
          "rakeCap": "$2.50 cap",
          "rule": "No flop no drop (rake is taken only when the hand goes to a flop)",
          "operators": "PokerStars"
        }
      },
      {
        "file": "PLO_6_200_1.00-2.00.json",
        "value": "200",
        "data": {
          "rank": "1",
          "network": "PokerStars",
          "currency": "$9.30",
          "bigBlinds": "4.65 BB",
          "netRake": "2.44%",
          "rakePercentage": "5.00%",
          "rakeCap": "$2.75 cap",
          "rule": "No flop no drop (rake is taken only when the hand goes to a flop)",
          "operators": "PokerStars"
        }
      },
      {
        "file": "PLO_6_500_2.50-5.00.json",
        "value": "500",
        "data": {
          "rank": "1",
          "network": "PokerStars",
          "currency": "$15.75",
          "bigBlinds": "3.15 BB",
          "netRake": "1.65%",
          "rakePercentage": "5.00%",
          "rakeCap": "$3.00 cap",
          "rule": "No flop no drop (rake is taken only when the hand goes to a flop)",
          "operators": "PokerStars"
        }
      }
    ],
    "name": "PokerStars"
  },
  {
    "network": [
      {
        "file": "PLO_6_10_0.05-0.10.json",
        "value": "10",
        "data": {
          "rank": "11",
          "network": "PokerStars Europe",
          "currency": "€1.05",
          "bigBlinds": "10.54 BB",
          "netRake": "5.28%",
          "rakePercentage": "6.00%",
          "rakeCap": "€1.25 cap",
          "rule": "No flop no drop (rake is taken only when the hand goes to a flop)",
          "operators": "PokerStars"
        }
      },
      {
        "file": "PLO_6_25_0.10-0.25.json",
        "value": "25",
        "data": {
          "rank": "11",
          "network": "PokerStars Europe",
          "currency": "€2.51",
          "bigBlinds": "10.06 BB",
          "netRake": "5.03%",
          "rakePercentage": "5.75%",
          "rakeCap": "€2.85 cap",
          "rule": "No flop no drop (rake is taken only when the hand goes to a flop)",
          "operators": "PokerStars"
        }
      },
      {
        "file": "PLO_6_50_0.25-0.50.json",
        "value": "50",
        "data": {
          "rank": "11",
          "network": "PokerStars Europe",
          "currency": "€4.50",
          "bigBlinds": "9.01 BB",
          "netRake": "4.44%",
          "rakePercentage": "5.75%",
          "rakeCap": "€3.00 cap",
          "rule": "No flop no drop (rake is taken only when the hand goes to a flop)",
          "operators": "PokerStars"
        }
      },
      {
        "file": "PLO_6_100_0.50-1.00.json",
        "value": "100",
        "data": {
          "rank": "10",
          "network": "PokerStars Europe",
          "currency": "€7.84",
          "bigBlinds": "7.84 BB",
          "netRake": "3.78%",
          "rakePercentage": "5.75%",
          "rakeCap": "€3.00 cap",
          "rule": "No flop no drop (rake is taken only when the hand goes to a flop)",
          "operators": "PokerStars"
        }
      },
      {
        "file": "PLO_6_200_1.00-2.00.json",
        "value": "200",
        "data": {
          "rank": "4",
          "network": "PokerStars Europe",
          "currency": "€10.46",
          "bigBlinds": "5.23 BB",
          "netRake": "2.74%",
          "rakePercentage": "5.75%",
          "rakeCap": "€3.00 cap",
          "rule": "No flop no drop (rake is taken only when the hand goes to a flop)",
          "operators": "PokerStars"
        }
      },
      {
        "file": "PLO_6_500_2.50-5.00.json",
        "value": "500",
        "data": {
          "rank": "3",
          "network": "PokerStars Europe",
          "currency": "€16.75",
          "bigBlinds": "3.35 BB",
          "netRake": "1.76%",
          "rakePercentage": "5.75%",
          "rakeCap": "€3.00 cap",
          "rule": "No flop no drop (rake is taken only when the hand goes to a flop)",
          "operators": "PokerStars"
        }
      }
    ],
    "name": "PokerStars Europe"
  },
  {
    "network": [
      {
        "file": "PLO_6_10_0.05-0.10.json",
        "value": "10",
        "data": {
          "rank": "1",
          "network": "",
          "currency": "€0.54",
          "bigBlinds": "5.35 BB",
          "netRake": "2.68%",
          "rakePercentage": "3.00%",
          "rakeCap": "€2.00 cap",
          "rule": "No flop no drop (rake is taken only when the hand goes to a flop)",
          "operators": "Unibet"
        }
      },
      {
        "file": "PLO_6_25_0.10-0.25.json",
        "value": "25",
        "data": {
          "rank": "7",
          "network": "",
          "currency": "€2.21",
          "bigBlinds": "8.85 BB",
          "netRake": "4.43%",
          "rakePercentage": "5.00%",
          "rakeCap": "€3.00 cap",
          "rule": "No flop no drop (rake is taken only when the hand goes to a flop)",
          "operators": "Unibet"
        }
      },
      {
        "file": "PLO_6_50_0.25-0.50.json",
        "value": "50",
        "data": {
          "rank": "10",
          "network": "",
          "currency": "€4.35",
          "bigBlinds": "8.69 BB",
          "netRake": "4.28%",
          "rakePercentage": "5.50%",
          "rakeCap": "€3.00 cap",
          "rule": "No flop no drop (rake is taken only when the hand goes to a flop)",
          "operators": "Unibet"
        }
      },
      {
        "file": "PLO_6_100_0.50-1.00.json",
        "value": "100",
        "data": {
          "rank": "12",
          "network": "",
          "currency": "€8.08",
          "bigBlinds": "8.08 BB",
          "netRake": "3.89%",
          "rakePercentage": "6.00%",
          "rakeCap": "€3.00 cap",
          "rule": "No flop no drop (rake is taken only when the hand goes to a flop)",
          "operators": "Unibet"
        }
      },
      {
        "file": "PLO_6_200_1.00-2.00.json",
        "value": "200",
        "data": {
          "rank": "10",
          "network": "",
          "currency": "€10.73",
          "bigBlinds": "5.36 BB",
          "netRake": "2.81%",
          "rakePercentage": "6.00%",
          "rakeCap": "€3.00 cap",
          "rule": "No flop no drop (rake is taken only when the hand goes to a flop)",
          "operators": "Unibet"
        }
      },
      {
        "file": "PLO_6_500_2.50-5.00.json",
        "value": "500",
        "data": {
          "rank": "5",
          "network": "",
          "currency": "€17.06",
          "bigBlinds": "3.41 BB",
          "netRake": "1.79%",
          "rakePercentage": "6.00%",
          "rakeCap": "€3.00 cap",
          "rule": "No flop no drop (rake is taken only when the hand goes to a flop)",
          "operators": "Unibet"
        }
      }
    ],
    "name": "Unibet"
  },
  {
    "network": [
      {
        "file": "PLO_6_10_0.05-0.10.json",
        "value": "10",
        "data": {
          "rank": "10",
          "network": "",
          "currency": "€1.02",
          "bigBlinds": "10.20 BB",
          "netRake": "5.11%",
          "rakePercentage": "5.75%",
          "rakeCap": "€1.50 cap",
          "rule": "No flop no drop (rake is taken only when the hand goes to a flop)",
          "operators": "Winamax.fr"
        }
      },
      {
        "file": "PLO_6_25_0.10-0.25.json",
        "value": "25",
        "data": {
          "rank": "12",
          "network": "",
          "currency": "€2.53",
          "bigBlinds": "10.11 BB",
          "netRake": "5.06%",
          "rakePercentage": "5.75%",
          "rakeCap": "€3.00 cap",
          "rule": "No flop no drop (rake is taken only when the hand goes to a flop)",
          "operators": "Winamax.fr"
        }
      },
      {
        "file": "PLO_6_50_0.25-0.50.json",
        "value": "50",
        "data": {
          "rank": "11",
          "network": "",
          "currency": "€4.50",
          "bigBlinds": "9.01 BB",
          "netRake": "4.44%",
          "rakePercentage": "5.75%",
          "rakeCap": "€3.00 cap",
          "rule": "No flop no drop (rake is taken only when the hand goes to a flop)",
          "operators": "Winamax.fr"
        }
      },
      {
        "file": "PLO_6_100_0.50-1.00.json",
        "value": "100",
        "data": {
          "rank": "10",
          "network": "",
          "currency": "€7.84",
          "bigBlinds": "7.84 BB",
          "netRake": "3.78%",
          "rakePercentage": "5.75%",
          "rakeCap": "€3.00 cap",
          "rule": "No flop no drop (rake is taken only when the hand goes to a flop)",
          "operators": "Winamax.fr"
        }
      },
      {
        "file": "PLO_6_200_1.00-2.00.json",
        "value": "200",
        "data": {
          "rank": "4",
          "network": "",
          "currency": "€10.46",
          "bigBlinds": "5.23 BB",
          "netRake": "2.74%",
          "rakePercentage": "5.75%",
          "rakeCap": "€3.00 cap",
          "rule": "No flop no drop (rake is taken only when the hand goes to a flop)",
          "operators": "Winamax.fr"
        }
      },
      {
        "file": "PLO_6_500_2.50-5.00.json",
        "value": "500",
        "data": {
          "rank": "3",
          "network": "",
          "currency": "€16.75",
          "bigBlinds": "3.35 BB",
          "netRake": "1.76%",
          "rakePercentage": "5.75%",
          "rakeCap": "€3.00 cap",
          "rule": "No flop no drop (rake is taken only when the hand goes to a flop)",
          "operators": "Winamax.fr"
        }
      }
    ],
    "name": "Winamax.fr"
  },
  {
    "network": [
      {
        "file": "PLO_6_10_0.05-0.10.json",
        "value": "10",
        "data": {
          "rank": "8",
          "network": "Winning Poker",
          "currency": "$0.89",
          "bigBlinds": "8.92 BB",
          "netRake": "4.46%",
          "rakePercentage": "5.00%",
          "rakeCap": "$3.00 cap",
          "rule": "No flop no drop (rake is taken only when the hand goes to a flop)",
          "operators": "Americas CardroomBlack Chip Poker"
        }
      },
      {
        "file": "PLO_6_25_0.10-0.25.json",
        "value": "25",
        "data": {
          "rank": "7",
          "network": "Winning Poker",
          "currency": "$2.21",
          "bigBlinds": "8.85 BB",
          "netRake": "4.43%",
          "rakePercentage": "5.00%",
          "rakeCap": "$3.00 cap",
          "rule": "No flop no drop (rake is taken only when the hand goes to a flop)",
          "operators": "Americas CardroomBlack Chip Poker"
        }
      },
      {
        "file": "PLO_6_50_0.25-0.50.json",
        "value": "50",
        "data": {
          "rank": "5",
          "network": "Winning Poker",
          "currency": "$4.02",
          "bigBlinds": "8.04 BB",
          "netRake": "3.96%",
          "rakePercentage": "5.00%",
          "rakeCap": "$3.00 cap",
          "rule": "No flop no drop (rake is taken only when the hand goes to a flop)",
          "operators": "Americas CardroomBlack Chip Poker"
        }
      },
      {
        "file": "PLO_6_100_0.50-1.00.json",
        "value": "100",
        "data": {
          "rank": "4",
          "network": "Winning Poker",
          "currency": "$7.10",
          "bigBlinds": "7.10 BB",
          "netRake": "3.42%",
          "rakePercentage": "5.00%",
          "rakeCap": "$3.00 cap",
          "rule": "No flop no drop (rake is taken only when the hand goes to a flop)",
          "operators": "Americas CardroomBlack Chip Poker"
        }
      },
      {
        "file": "PLO_6_200_1.00-2.00.json",
        "value": "200",
        "data": {
          "rank": "2",
          "network": "Winning Poker",
          "currency": "$9.63",
          "bigBlinds": "4.81 BB",
          "netRake": "2.52%",
          "rakePercentage": "5.00%",
          "rakeCap": "$3.00 cap",
          "rule": "No flop no drop (rake is taken only when the hand goes to a flop)",
          "operators": "Americas CardroomBlack Chip Poker"
        }
      },
      {
        "file": "PLO_6_500_2.50-5.00.json",
        "value": "500",
        "data": {
          "rank": "1",
          "network": "Winning Poker",
          "currency": "$15.75",
          "bigBlinds": "3.15 BB",
          "netRake": "1.65%",
          "rakePercentage": "5.00%",
          "rakeCap": "$3.00 cap",
          "rule": "No flop no drop (rake is taken only when the hand goes to a flop)",
          "operators": "Americas CardroomBlack Chip Poker"
        }
      }
    ],
    "name": "Winning Poker"
  }
]